sark0y_tam/__init__.py
sark0y_tam/__main__.py
sark0y_tam/_subTern.py
sark0y_tam/_tam.py
sark0y_tam-1.9.121.dist-info/licenses/LICENSE.TXT
sark0y_tam-1.9.121.dist-info/METADATA
sark0y_tam-1.9.121.dist-info/WHEEL
sark0y_tam-1.9.121.dist-info/top_level.txt
sark0y_tam-1.9.121.dist-info/RECORD
