Metadata-Version: 2.4
Name: sark0y_tam
Version: 1.9.121
Summary: python3 -m sark0y_tam -ver and https://t.me/+N_TdOq7Ui2ZiOTM6 to know more ;D
Author-email: "Evgeney Knyazhev (SarK0Y)" <sark0y@protonmail.com>
License: Personal usage will cost You $0.00, but don't be shy to donate me.. or You could support me any other way You want - just call/mail me to discuss possible variants for mutual gains. 🙂
Project-URL: Homepage, https://t.me/+N_TdOq7Ui2ZiOTM6
Classifier: Programming Language :: Python :: 3.9
Classifier: License :: Free for non-commercial use
Classifier: Operating System :: POSIX :: Linux
Requires-Python: >=3.9
License-File: LICENSE.TXT
Requires-Dist: keyboard
Requires-Dist: numpy
Requires-Dist: tabulate
Requires-Dist: click
Requires-Dist: colorama
Requires-Dist: setuptools
Dynamic: license-file
